rpi_backlight_emulator/__init__.py
rpi_backlight_emulator/images/display_off.png
rpi_backlight_emulator/images/display_on.png
rpi_backlight_emulator/images/icon.png
rpi_backlight_emulator/images/raspbian.png
rpi_backlight_emulator-1.2.0.dist-info/LICENSE
rpi_backlight_emulator-1.2.0.dist-info/METADATA
rpi_backlight_emulator-1.2.0.dist-info/WHEEL
rpi_backlight_emulator-1.2.0.dist-info/entry_points.txt
rpi_backlight_emulator-1.2.0.dist-info/top_level.txt
rpi_backlight_emulator-1.2.0.dist-info/RECORD
