Metadata-Version: 2.1
Name: rpi-backlight-emulator
Version: 1.2.0
Summary: Raspberry Pi 7" LCD emulator for rpi-backlight
Home-page: https://github.com/linusg/rpi-backlight-emulator
Author: Linus Groh
Author-email: mail@linusgroh.de
License: MIT
Download-URL: https://pypi.org/project/rpi-backlight-emulator
Keywords: raspberry pi,display,touchscreen,brightness,backlight,emulator
Platform: UNKNOWN
Classifier: Development Status :: 5 - Production/Stable
Classifier: Intended Audience :: Developers
Classifier: License :: OSI Approved :: MIT License
Classifier: Operating System :: MacOS
Classifier: Operating System :: Microsoft :: Windows
Classifier: Operating System :: Unix
Classifier: Programming Language :: Python
Classifier: Programming Language :: Python :: 3.5
Classifier: Programming Language :: Python :: 3.6
Classifier: Programming Language :: Python :: 3.7
Classifier: Programming Language :: Python :: 3.8
Classifier: Programming Language :: Python :: 3 :: Only
Classifier: Topic :: System
Classifier: Topic :: System :: Emulators
Classifier: Topic :: System :: Hardware
Classifier: Topic :: Multimedia
Classifier: Topic :: Utilities
Requires-Dist: watchdog
Requires-Dist: PySide2
Requires-Dist: rpi-backlight (>=2.0.0)
